autodevops_cli/__init__.py
autodevops_cli/cli.py
autodevops_cli/setup_cli.py
autodevops_cli/setup_cli_old.py
autodevops_cli/test_main.py
autodevops_cli-8.0.dist-info/METADATA
autodevops_cli-8.0.dist-info/WHEEL
autodevops_cli-8.0.dist-info/entry_points.txt
autodevops_cli-8.0.dist-info/top_level.txt
autodevops_cli-8.0.dist-info/RECORD
