Metadata-Version: 2.1
Name: autodevops-cli
Version: 8.0
Summary: AI-powered CLI tool for automating DevOps workflows like setup, Git, CI/CD, Docker, and documentation.
Home-page: https://github.com/kannanb2745/Automated-DevOps
Author: Kannan
Author-email: kannan@example.com
Classifier: Programming Language :: Python :: 3
Classifier: License :: OSI Approved :: MIT License
Classifier: Operating System :: OS Independent
Classifier: Development Status :: 5 - Production/Stable
Classifier: Intended Audience :: Developers
Classifier: Topic :: Software Development :: Build Tools
Requires-Python: >=3.6
Requires-Dist: click
Requires-Dist: loguru
Requires-Dist: openai
Requires-Dist: python-dotenv
Requires-Dist: rich
Requires-Dist: sh
